{
  "problem": "The graph shows the total  distance Sam drove from    6 a.m to 11 a.m.  How many  miles per hour is the car's  average speed for the period  from 6 a.m. to 11 a.m.?\n\n[asy]\nunitsize(0.2inch);\ndraw((0,0)--(5.5,0));\ndraw((0,0)--(0,8.5));\ndraw((1,0)--(1,8.5));\ndraw((2,0)--(2,8.5));\ndraw((3,0)--(3,8.5));\ndraw((4,0)--(4,8.5));\ndraw((5,0)--(5,8.5));\ndraw((0,1)--(5.5,1));\ndraw((0,8)--(5.5,8));\ndraw((0,7)--(5.5,7));\ndraw((0,6)--(5.5,6));\ndraw((0,5)--(5.5,5));\ndraw((0,4)--(5.5,4));\ndraw((0,3)--(5.5,3));\ndraw((0,2)--(5.5,2));\ndraw((0,0)--(1,2)--(2,3)--(3,5)--(4,6)--(5,8));\ndot((0,0));\ndot((1,2));\ndot((2,3));\ndot((3,5));\ndot((4,6));\ndot((5,8));\nlabel(\"6\",(0,-0.5),S);\nlabel(\"7\",(1,-0.5),S);\nlabel(\"8\",(2,-0.5),S);\nlabel(\"9\",(3,-0.5),S);\nlabel(\"10\",(4,-0.5),S);\nlabel(\"11\",(5,-0.5),S);\nlabel(\"0\",(-0.5,0),W);\nlabel(\"40\",(-0.5,2),W);\nlabel(\"80\",(-0.5,4),W);\nlabel(\"120\",(-0.5,6),W);\nlabel(\"160\",(-0.5,8),W);\nlabel(\"Time of Day (a.m.)\",(2.7,-2),S);\nlabel(\"Total distance\",(-0.5,9),N);\n[/asy]",
  "all_solutions": [
    "To find the average speed of the car from 6 a.m. to 11 a.m., we need to calculate the total distance traveled and the time taken.\n\nFrom the graph, we can see that the total distance traveled is 160 miles.\n\nThe time taken from 6 a.m. to 11 a.m. is 5 hours.\n\nNow, to find the average speed, we divide the total distance traveled (160 miles) by the time taken (5 hours).\n\nAverage speed = Total distance / Time\n= 160 miles / 5 hours\n= 32 miles per hour\n\nSo, the average speed of the car from 6 a.m. to 11 a.m. is 32 miles per hour.\n\n$\\boxed{32}$",
    "To find the average speed of the car, we need to divide the total distance traveled by the total time taken. \n\nThe total distance traveled from 6 a.m to 11 a.m is 160 miles. The total time taken is 5 hours (from 6 a.m to 11 a.m).\n\nTo calculate the average speed, we divide the total distance by the total time.\n\nAverage speed = Total distance / Total time\n= 160 miles / 5 hours\n= 32 miles per hour\n\nSo, the average speed of the car for the period from 6 a.m to 11 a.m is 32 miles per hour.\n\n$\\boxed{32}$",
    "To find the average speed of Sam's car during the period from 6 a.m. to 11 a.m., we need to find the total distance traveled and the total time taken.\n\nStep 1: Find the total distance traveled by Sam from 6 a.m. to 11 a.m. \nFrom the graph, the total distance traveled is 160 miles.\n\nStep 2: Find the total time taken by Sam from 6 a.m. to 11 a.m.\nThe time taken is from 6 a.m. to 11 a.m. which is 5 hours.\n\nStep 3: Calculate the average speed of Sam's car.\nTo calculate the average speed, we need to divide the total distance traveled by the total time taken.\n\nAverage Speed = Total Distance / Total Time\nAverage Speed = 160 miles / 5 hours\nAverage Speed = 32 miles per hour\n\nTherefore, the average speed of Sam's car from 6 a.m. to 11 a.m. is $\\boxed{32}$."
  ],
  "model_solution": "To find the average speed of the car, we need to divide the total distance traveled by the total time taken. \n\nThe total distance traveled from 6 a.m to 11 a.m is 160 miles. The total time taken is 5 hours (from 6 a.m to 11 a.m).\n\nTo calculate the average speed, we divide the total distance by the total time.\n\nAverage speed = Total distance / Total time\n= 160 miles / 5 hours\n= 32 miles per hour\n\nSo, the average speed of the car for the period from 6 a.m to 11 a.m is 32 miles per hour.\n\n$\\boxed{32}$",
  "critique": "The best solution is Solution 1.",
  "solution": "Since he traveled 160 miles in 5 hours, his speed measured in miles per hour is $\\frac{160}{5} = \\boxed{32}$.",
  "level": "Level 5",
  "type": "Prealgebra",
  "total_tokens": 2158,
  "time_taken": 4.425156116485596
}