{
    "problem": "It takes Michael 0.30 hours to walk to school. How many seconds does it take him to walk to school?",
    "level": "Level 4",
    "type": "Prealgebra",
    "solution": "There are 60 minutes in an hour, and 60 seconds in a minute, so there are $60\\cdot60=3600$ seconds in an hour. Therefore, it takes Michael $(.30)(3600)=\\boxed{1080}$ seconds to walk to school.",
    "is_solved": true,
    "model_solution": "Step 1: Convert the time from hours to minutes by multiplying 0.30 hours by 60 minutes/hour.\nStep 2: Convert the time from minutes to seconds by multiplying the time in minutes by 60 seconds/minute.\nStep 2: Multiply 18 minutes by 60 seconds/minute.\nStep 3: 1,080 seconds\nFinal Answer: The final answer is: 1080",
    "steps": [
        "Step 1: Convert the time from hours to minutes by multiplying 0.30 hours by 60 minutes/hour.",
        "Step 2: Convert the time from minutes to seconds by multiplying the time in minutes by 60 seconds/minute.",
        "Step 2: Multiply 18 minutes by 60 seconds/minute.",
        "Step 3: 1,080 seconds",
        "Final Answer: The final answer is: 1080"
    ],
    "full_steps": [
        [
            "Step 1: Convert the time from hours to minutes by multiplying 0.30 hours by 60 minutes/hour.",
            1
        ],
        [
            "Step 2: Convert the time from minutes to seconds by multiplying the time in minutes by 60 seconds/minute.",
            1
        ],
        [
            "Step 2: Multiply 18 minutes by 60 seconds/minute.",
            1
        ],
        [
            "Step 3: 1,080 seconds",
            1
        ],
        [
            "Final Answer: The final answer is: 1080",
            1
        ]
    ],
    "time": 67.17352747917175,
    "total_tokens": 1480,
    "final_answer_tokens": 168,
    "model": "meta-llama/Llama-Vision-Free"
}