{
    "problem": "For what positive value of $t$ is $|{-4+ti}| = 6$?",
    "level": "Level 2",
    "type": "Intermediate Algebra",
    "solution": "Since $|{-4+ti}| = \\sqrt{(-4)^2 + t^2} = \\sqrt{t^2+16}$, the equation $|{-4+ti}| = 6$ tells us that $\\sqrt{t^2 + 16} = 6$.  Squaring both sides gives $t^2 + 16= 36$, so $t^2= 20$.  Since we want the positive value of $t$, we have $t = \\boxed{2\\sqrt5}$.",
    "is_solved": false,
    "model_solution": "Step 1: Square both sides of the equation $|{-4+ti}| = 6$ to eliminate the absolute value.\nStep 2: Evaluate the expression on the left side using the fact that $|a+bi| = \\sqrt{a^2+b^2}$.\nStep 3: Write the equation as $16 + t^2 = 36$\nStep 4: Solve for $t$: $t^2 = 20$.\n$t = \\sqrt{20} = 2 \\sqrt{5}$\nStep 5: $t = \\pm 2 \\sqrt{5}$\nSince we need a positive value of $t$, the solution is $t = 2\\sqrt{5}$.\nStep 6: $t = \\boxed{2\\sqrt{5}}$\nStep 4: Solve for t: t2 = 20.\nt = \u00b1\u221a20",
    "steps": [
        "Step 1: Square both sides of the equation $|{-4+ti}| = 6$ to eliminate the absolute value.",
        "Step 2: Evaluate the expression on the left side using the fact that $|a+bi| = \\sqrt{a^2+b^2}$.",
        "Step 3: Write the equation as $16 + t^2 = 36$",
        "Step 4: Solve for $t$: $t^2 = 20$.",
        "$t = \\sqrt{20} = 2 \\sqrt{5}$",
        "Step 5: $t = \\pm 2 \\sqrt{5}$",
        "Since we need a positive value of $t$, the solution is $t = 2\\sqrt{5}$.",
        "Step 6: $t = \\boxed{2\\sqrt{5}}$",
        "Step 4: Solve for t: t2 = 20.",
        "t = \u00b1\u221a20"
    ],
    "full_steps": [
        [
            "Step 1: Square both sides of the equation $|{-4+ti}| = 6$ to eliminate the absolute value.",
            1
        ],
        [
            "Step 2: Evaluate the expression on the left side using the fact that $|a+bi| = \\sqrt{a^2+b^2}$.",
            1
        ],
        [
            "Step 3: Write the equation as $16 + t^2 = 36$",
            1
        ],
        [
            "Step 4: Solve for $t$: $t^2 = 20$.",
            1
        ],
        [
            "$t = \\sqrt{20} = 2 \\sqrt{5}$",
            1
        ],
        [
            "Step 5: $t = \\pm 2 \\sqrt{5}$",
            1
        ],
        [
            "Since we need a positive value of $t$, the solution is $t = 2\\sqrt{5}$.",
            1
        ],
        [
            "Step 6: $t = \\boxed{2\\sqrt{5}}$",
            1
        ],
        [
            "Step 4: Solve for t: t2 = 20.",
            1
        ],
        [
            "t = \u00b1\u221a20",
            1
        ]
    ],
    "time": 130.80480813980103,
    "total_tokens": 4107,
    "final_answer_tokens": 0,
    "model": "meta-llama/Llama-Vision-Free"
}