{
    "problem": "If $(2x+5)(x-3)=14$, find the sum of the possible values of $x$.",
    "level": "Level 4",
    "type": "Algebra",
    "solution": "Expanding the left side of the given equation, we have $2x^2-x-15=14 \\Rightarrow 2x^2-x-29=0$. Since in a quadratic with equation of the form $ax^2+bx+c=0$ the sum of the roots is $-b/a$, the sum of the roots of the given equation is $1/2=\\boxed{.5}$.",
    "is_solved": true,
    "model_solution": "Step 1: Expand the left side of the equation: $2x^2 - 6x + 5x - 15 = 14$\nStep 2: Simplify the equation: $2x^2 - x - 15 = 14$\nStep 3: Subtract 14 from both sides of the equation: $2x^2 - x - 29 = 0$\nStep 4: Use the quadratic formula: $x = \\frac{-b \\pm \\sqrt{b^2-4ac}}{2a}$\nStep 5: Plug in the values $a = 2$, $b = -1$, and $c = -29$ into the quadratic formula: $x = \\frac{-(-1) \\pm \\sqrt{(-1)^2 - 4(2)(-29)}}{2(2)}$\n$x = \\frac{1 \\pm \\sqrt{229}}{4}$\nSince we have two possible values of x, we need to add them together.\n\n$x_1 + x_2 = \\frac{1 + \\sqrt{229}}{4} + \\frac{1 - \\sqrt{229}}{4}$ \n\nFinal Answer",
    "steps": [
        "Step 1: Expand the left side of the equation: $2x^2 - 6x + 5x - 15 = 14$",
        "Step 2: Simplify the equation: $2x^2 - x - 15 = 14$",
        "Step 3: Subtract 14 from both sides of the equation: $2x^2 - x - 29 = 0$",
        "Step 4: Use the quadratic formula: $x = \\frac{-b \\pm \\sqrt{b^2-4ac}}{2a}$",
        "Step 5: Plug in the values $a = 2$, $b = -1$, and $c = -29$ into the quadratic formula: $x = \\frac{-(-1) \\pm \\sqrt{(-1)^2 - 4(2)(-29)}}{2(2)}$",
        "$x = \\frac{1 \\pm \\sqrt{229}}{4}$",
        "Since we have two possible values of x, we need to add them together.\n\n$x_1 + x_2 = \\frac{1 + \\sqrt{229}}{4} + \\frac{1 - \\sqrt{229}}{4}$ \n\nFinal Answer"
    ],
    "full_steps": [
        [
            "Step 1: Expand the left side of the equation: $2x^2 - 6x + 5x - 15 = 14$",
            1
        ],
        [
            "Step 2: Simplify the equation: $2x^2 - x - 15 = 14$",
            1
        ],
        [
            "Step 3: Subtract 14 from both sides of the equation: $2x^2 - x - 29 = 0$",
            1
        ],
        [
            "Step 4: Use the quadratic formula: $x = \\frac{-b \\pm \\sqrt{b^2-4ac}}{2a}$",
            1
        ],
        [
            "Step 5: Plug in the values $a = 2$, $b = -1$, and $c = -29$ into the quadratic formula: $x = \\frac{-(-1) \\pm \\sqrt{(-1)^2 - 4(2)(-29)}}{2(2)}$",
            1
        ],
        [
            "$x = \\frac{1 \\pm \\sqrt{229}}{4}$",
            1
        ],
        [
            "Since we have two possible values of x, we need to add them together.\n\n$x_1 + x_2 = \\frac{1 + \\sqrt{229}}{4} + \\frac{1 - \\sqrt{229}}{4}$ \n\nFinal Answer",
            1
        ]
    ],
    "time": 96.28329658508301,
    "total_tokens": 3071,
    "final_answer_tokens": 335,
    "model": "meta-llama/Llama-Vision-Free"
}