{
    "problem": "Simplify $(5x+3) - 2(2x-4)$.",
    "level": "Level 4",
    "type": "Prealgebra",
    "solution": "First, we can rewrite the whole expression as $(5x+3) + [-2(2x-4)]$.  Distributing the second part, we have $-2(2x-4) = -4x +8$.  Substituting this into our big expression, we have $(5x+3) + (-4x +8)$.  Combining like terms, we get $(5x - 4x) + (3 + 8)$.  This yields $\\boxed{x+11}$ or $\\boxed{11+x}$.",
    "is_solved": true,
    "model_solution": "Distribute the -2 to the terms in the parentheses.\nCombine like terms.\n$=5x+3-4x+8$\nCombine like terms.\n$=x+11$\n$x+11$\nCombine like terms.\n$x+11$\n$=x+11$\n= x + 11\n$=x+11$",
    "steps": [
        "Distribute the -2 to the terms in the parentheses.",
        "Combine like terms.",
        "$=5x+3-4x+8$",
        "Combine like terms.\n$=x+11$",
        "$x+11$",
        "Combine like terms.\n$x+11$",
        "$=x+11$",
        "= x + 11",
        "$=x+11$"
    ],
    "full_steps": [
        [
            "Distribute the -2 to the terms in the parentheses.",
            1
        ],
        [
            "Combine like terms.",
            1
        ],
        [
            "$=5x+3-4x+8$",
            1
        ],
        [
            "Combine like terms.\n$=x+11$",
            1
        ],
        [
            "$x+11$",
            1
        ],
        [
            "Combine like terms.\n$x+11$",
            1
        ],
        [
            "$=x+11$",
            1
        ],
        [
            "= x + 11",
            1
        ],
        [
            "$=x+11$",
            1
        ]
    ],
    "time": 115.40801525115967,
    "total_tokens": 2205,
    "final_answer_tokens": 144,
    "model": "meta-llama/Llama-Vision-Free"
}