{
    "problem": "Find all solutions to the equation $\\displaystyle\\sqrt[3]{2 - \\frac{x}{2}} = -3$.",
    "level": "Level 3",
    "type": "Algebra",
    "solution": "We get rid of the cube root sign by cubing both sides.  This gives us $2-\\frac{x}{2} = -27$.  Solving this equation gives $x =\\boxed{58}$.",
    "is_solved": true,
    "model_solution": "Step 1: Cube both sides of the equation to get $\\left(\\displaystyle\\sqrt[3]{2 - \\frac{x}{2}}\\right)^3 = (-3)^3$.\nStep 2: Simplify the equation to get $2 - \\frac{x}{2} = -27$.\nStep 3: Subtract 2 from both sides and multiply both sides by 2 to get $-x = -58$.\nStep 4: Multiply both sides by -1 to get x = 58.\nFinal Answer: x = 58",
    "steps": [
        "Step 1: Cube both sides of the equation to get $\\left(\\displaystyle\\sqrt[3]{2 - \\frac{x}{2}}\\right)^3 = (-3)^3$.",
        "Step 2: Simplify the equation to get $2 - \\frac{x}{2} = -27$.",
        "Step 3: Subtract 2 from both sides and multiply both sides by 2 to get $-x = -58$.",
        "Step 4: Multiply both sides by -1 to get x = 58.",
        "Final Answer: x = 58"
    ],
    "full_steps": [
        [
            "Step 1: Cube both sides of the equation to get $\\left(\\displaystyle\\sqrt[3]{2 - \\frac{x}{2}}\\right)^3 = (-3)^3$.",
            1
        ],
        [
            "Step 2: Simplify the equation to get $2 - \\frac{x}{2} = -27$.",
            1
        ],
        [
            "Step 3: Subtract 2 from both sides and multiply both sides by 2 to get $-x = -58$.",
            1
        ],
        [
            "Step 4: Multiply both sides by -1 to get x = 58.",
            1
        ],
        [
            "Final Answer: x = 58",
            1
        ]
    ],
    "time": 66.95593619346619,
    "total_tokens": 1747,
    "final_answer_tokens": 201,
    "model": "meta-llama/Llama-Vision-Free"
}