{
    "problem": "Compute $\\sin^3 18^\\circ + \\sin^2 18^\\circ.$",
    "level": "Level 3",
    "type": "Precalculus",
    "solution": "We can write\n\\begin{align*}\n\\sin^3 18^\\circ + \\sin^2 18^\\circ &= \\sin^2 18^\\circ (\\sin 18^\\circ + 1) \\\\\n&= \\sin^2 18^\\circ (\\sin 18^\\circ + \\sin 90^\\circ).\n\\end{align*}By sum-to-product,\n\\begin{align*}\n\\sin^2 18^\\circ (\\sin 18^\\circ + \\sin 90^\\circ) &= \\sin^2 18^\\circ \\cdot 2 \\sin 54^\\circ \\cos 36^\\circ \\\\\n&= 2 \\sin^2 18^\\circ \\cos^2 36^\\circ \\\\\n&= \\frac{2 \\sin^2 18^\\circ \\cos^2 18^\\circ \\cos^2 36^\\circ}{\\cos^2 18^\\circ} \\\\\n&= \\frac{4 \\sin^2 18^\\circ \\cos^2 18^\\circ \\cos^2 36^\\circ}{2 \\cos^2 18^\\circ}.\n\\end{align*}Then by double angle formula,\n\\begin{align*}\n\\frac{4 \\sin^2 18^\\circ \\cos^2 18^\\circ \\cos^2 36^\\circ}{2 \\cos^2 18^\\circ} &= \\frac{\\sin^2 36^\\circ \\cos^2 36^\\circ}{2 \\cos^2 18^\\circ} \\\\\n&= \\frac{4 \\sin^2 36^\\circ \\cos^2 36^\\circ}{8 \\cos^2 18^\\circ} \\\\\n&= \\frac{\\sin^2 72^\\circ}{8 \\cos^2 18^\\circ} \\\\\n&= \\boxed{\\frac{1}{8}}.\n\\end{align*}Alternatively, we can plug in the value $\\sin 18^\\circ = \\frac{\\sqrt{5} - 1}{4}.$",
    "is_solved": false,
    "model_solution": "## Step 1: Recall the given expression\n$\\sin^3 18^\\circ + \\sin^2 18^\\circ.$\n## Step 2: Apply the formula $\\sin^2 \\theta = \\frac{1 - \\cos 2 \\theta}{2}$\n$\\sin^3 18^\\circ + \\sin^2 18^\\circ = \\sin^2 18^\\circ(\\sin 18^\\circ + 1) = \\frac{1 - \\cos 36^\\circ}{2}(\\sin 18^\\circ + 1)$\n## Step 3: Apply the formula $\\sin \\theta = \\frac{1 - \\cos \\theta}{\\sin \\theta}$\n$\\frac{1 - \\cos 36^\\circ}{2}(\\sin 18^\\circ + 1) = \\frac{1 - \\cos 36^\\circ}{2} \\cdot \\frac{1 - \\cos 18^\\circ}{\\sin 18^\\circ}$\n## Step 4: Simplify the expression\n$\\frac{1 - \\cos 36^\\circ}{2} \\cdot \\frac{1 - \\cos 18^\\circ}{\\sin 18^\\circ} = \\frac{1 - \\cos 36^\\circ}{2 \\sin 18^\\circ}(1 - \\cos 18^\\circ)$\n## Step 5: Use the value of $\\cos 36^\\circ = \\frac{\\phi}{2}$ and $\\sin 18^\\circ = \\frac{\\sqrt{5} - 1}{4}$ where $\\phi = \\frac{1 + \\sqrt{5}}{2}$\n$\\frac{1 - \\frac{\\phi}{2}}{2 \\cdot \\frac{\\sqrt{5} - 1}{4}}(1 - \\frac{\\sqrt{5} - 1}{4})$\n## Step 6: Simplify the expression using the values of $\\phi$ and the calculation of $1 - \\frac{\\sqrt{5} - 1}{4}$\n$\\frac{1 - \\frac{\\phi}{2}}{2 \\cdot \\frac{\\sqrt{5} - 1}{4}}(1 - \\frac{\\sqrt{5} - 1}{4}) = \\frac{\\frac{2 - \\phi}{2}}{\\frac{\\sqrt{5} - 1}{2}} \\cdot \\frac{4 - \\sqrt{5} + 1}{4} = \\frac{2 - \\phi}{\\sqrt{5} - 1} \\cdot \\frac{5 - \\sqrt{5}}{4}$\n## Step 7: Simplify the expression using the values of $\\phi = \\frac{1 + \\sqrt{5}}{2}$\n$\\frac{2 - \\frac{1 + \\sqrt{5}}{2}}{\\sqrt{5} - 1} \\cdot \\frac{5 - \\sqrt{5}}{4} = \\frac{4 - 1 - \\sqrt{5}}{2(\\sqrt{5} - 1)} \\cdot \\frac{5 - \\sqrt{5}}{4} = \\frac{3 - \\sqrt{5}}{2(\\sqrt{5} - 1)} \\cdot \\frac{5 - \\sqrt{5}}{4}$",
    "steps": [
        "## Step 1: Recall the given expression\n$\\sin^3 18^\\circ + \\sin^2 18^\\circ.$",
        "## Step 2: Apply the formula $\\sin^2 \\theta = \\frac{1 - \\cos 2 \\theta}{2}$\n$\\sin^3 18^\\circ + \\sin^2 18^\\circ = \\sin^2 18^\\circ(\\sin 18^\\circ + 1) = \\frac{1 - \\cos 36^\\circ}{2}(\\sin 18^\\circ + 1)$",
        "## Step 3: Apply the formula $\\sin \\theta = \\frac{1 - \\cos \\theta}{\\sin \\theta}$\n$\\frac{1 - \\cos 36^\\circ}{2}(\\sin 18^\\circ + 1) = \\frac{1 - \\cos 36^\\circ}{2} \\cdot \\frac{1 - \\cos 18^\\circ}{\\sin 18^\\circ}$",
        "## Step 4: Simplify the expression\n$\\frac{1 - \\cos 36^\\circ}{2} \\cdot \\frac{1 - \\cos 18^\\circ}{\\sin 18^\\circ} = \\frac{1 - \\cos 36^\\circ}{2 \\sin 18^\\circ}(1 - \\cos 18^\\circ)$",
        "## Step 5: Use the value of $\\cos 36^\\circ = \\frac{\\phi}{2}$ and $\\sin 18^\\circ = \\frac{\\sqrt{5} - 1}{4}$ where $\\phi = \\frac{1 + \\sqrt{5}}{2}$\n$\\frac{1 - \\frac{\\phi}{2}}{2 \\cdot \\frac{\\sqrt{5} - 1}{4}}(1 - \\frac{\\sqrt{5} - 1}{4})$",
        "## Step 6: Simplify the expression using the values of $\\phi$ and the calculation of $1 - \\frac{\\sqrt{5} - 1}{4}$\n$\\frac{1 - \\frac{\\phi}{2}}{2 \\cdot \\frac{\\sqrt{5} - 1}{4}}(1 - \\frac{\\sqrt{5} - 1}{4}) = \\frac{\\frac{2 - \\phi}{2}}{\\frac{\\sqrt{5} - 1}{2}} \\cdot \\frac{4 - \\sqrt{5} + 1}{4} = \\frac{2 - \\phi}{\\sqrt{5} - 1} \\cdot \\frac{5 - \\sqrt{5}}{4}$",
        "## Step 7: Simplify the expression using the values of $\\phi = \\frac{1 + \\sqrt{5}}{2}$\n$\\frac{2 - \\frac{1 + \\sqrt{5}}{2}}{\\sqrt{5} - 1} \\cdot \\frac{5 - \\sqrt{5}}{4} = \\frac{4 - 1 - \\sqrt{5}}{2(\\sqrt{5} - 1)} \\cdot \\frac{5 - \\sqrt{5}}{4} = \\frac{3 - \\sqrt{5}}{2(\\sqrt{5} - 1)} \\cdot \\frac{5 - \\sqrt{5}}{4}$"
    ],
    "full_steps": [
        [
            "## Step 1: Recall the given expression\n$\\sin^3 18^\\circ + \\sin^2 18^\\circ.$",
            1
        ],
        [
            "## Step 2: Apply the formula $\\sin^2 \\theta = \\frac{1 - \\cos 2 \\theta}{2}$\n$\\sin^3 18^\\circ + \\sin^2 18^\\circ = \\sin^2 18^\\circ(\\sin 18^\\circ + 1) = \\frac{1 - \\cos 36^\\circ}{2}(\\sin 18^\\circ + 1)$",
            1
        ],
        [
            "## Step 3: Apply the formula $\\sin \\theta = \\frac{1 - \\cos \\theta}{\\sin \\theta}$\n$\\frac{1 - \\cos 36^\\circ}{2}(\\sin 18^\\circ + 1) = \\frac{1 - \\cos 36^\\circ}{2} \\cdot \\frac{1 - \\cos 18^\\circ}{\\sin 18^\\circ}$",
            1
        ],
        [
            "## Step 4: Simplify the expression\n$\\frac{1 - \\cos 36^\\circ}{2} \\cdot \\frac{1 - \\cos 18^\\circ}{\\sin 18^\\circ} = \\frac{1 - \\cos 36^\\circ}{2 \\sin 18^\\circ}(1 - \\cos 18^\\circ)$",
            1
        ],
        [
            "## Step 5: Use the value of $\\cos 36^\\circ = \\frac{\\phi}{2}$ and $\\sin 18^\\circ = \\frac{\\sqrt{5} - 1}{4}$ where $\\phi = \\frac{1 + \\sqrt{5}}{2}$\n$\\frac{1 - \\frac{\\phi}{2}}{2 \\cdot \\frac{\\sqrt{5} - 1}{4}}(1 - \\frac{\\sqrt{5} - 1}{4})$",
            1
        ],
        [
            "## Step 6: Simplify the expression using the values of $\\phi$ and the calculation of $1 - \\frac{\\sqrt{5} - 1}{4}$\n$\\frac{1 - \\frac{\\phi}{2}}{2 \\cdot \\frac{\\sqrt{5} - 1}{4}}(1 - \\frac{\\sqrt{5} - 1}{4}) = \\frac{\\frac{2 - \\phi}{2}}{\\frac{\\sqrt{5} - 1}{2}} \\cdot \\frac{4 - \\sqrt{5} + 1}{4} = \\frac{2 - \\phi}{\\sqrt{5} - 1} \\cdot \\frac{5 - \\sqrt{5}}{4}$",
            1
        ],
        [
            "## Step 7: Simplify the expression using the values of $\\phi = \\frac{1 + \\sqrt{5}}{2}$\n$\\frac{2 - \\frac{1 + \\sqrt{5}}{2}}{\\sqrt{5} - 1} \\cdot \\frac{5 - \\sqrt{5}}{4} = \\frac{4 - 1 - \\sqrt{5}}{2(\\sqrt{5} - 1)} \\cdot \\frac{5 - \\sqrt{5}}{4} = \\frac{3 - \\sqrt{5}}{2(\\sqrt{5} - 1)} \\cdot \\frac{5 - \\sqrt{5}}{4}$",
            1
        ]
    ],
    "time": 92.04930424690247,
    "total_tokens": 5775,
    "final_answer_tokens": 0,
    "model": "meta-llama/Llama-Vision-Free"
}