{
    "problem": "The numbers 1, 3, 6, 10, $\\ldots$, are called triangular numbers, as shown geometrically here.  What is the $20^{\\text{th}}$ triangular number?\n\n[asy]\n\ndot((0,0));\nlabel(\"1\",(0,-1.5));\n\ndot((3,0));\ndot((4,0));\ndot((3,1));\nlabel(\"3\",(3.5,-1.5));\n\ndot((7,0));\ndot((8,0));\ndot((9,0));\ndot((7,1));\ndot((7,2));\ndot((8,1));\nlabel(\"6\",(8,-1.5));\n\ndot((12,0));\ndot((13,0));\ndot((14,0));\ndot((15,0));\ndot((12,1));\ndot((13,1));\ndot((14,1));\ndot((12,2));\ndot((13,2));\ndot((12,3));\nlabel(\"10\",(13.5,-1.5));\n\n[/asy]",
    "level": "Level 3",
    "type": "Algebra",
    "solution": "The 20th triangular number is $1 + 2 + 3 + \\cdots + 20 = \\frac{(20)(21)}{2} = \\boxed{210}$.",
    "is_solved": true,
    "model_solution": "The $n^{\\text{th}}$ triangular number is the sum of the first $n$ positive integers, so we can write an equation for it: $a_n=1+2+3+\\ldots+n$.\n$Final\\ Answer.$\nFor the first step, we seek an expression for $a_n$ that allows us to determine the value of the $n^{\\text{th}}$ triangular number without having to sum the first $n$ positive integers.\nWe see that the $n^{\\text{th}}$ triangular number is equal to the sum of the first $n$ positive integers.\nWe note that this sum is equal to $1+2+3+\\ldots+(n-1)+n$.\nThis can be expressed more compactly as $\\frac{1}{2}n(n+1)$, using the formula for the sum of an arithmetic series.\nWe can evaluate this expression for $n=20$ by substituting $n=20$ into the formula, giving us $\\frac{1}{2}(20)(20+1)=\\frac{1}{2}(20)(21)=\\boxed{210}$.\nThe next step is:\nWe can evaluate this expression for $n=20$ by substituting $n=20$ into the formula, giving us $\\frac{1}{2}(20)(20+1)=\\frac{1}{2}(20)(21)=\\boxed{210}$.\nThe next step is: Final Answer.",
    "steps": [
        "The $n^{\\text{th}}$ triangular number is the sum of the first $n$ positive integers, so we can write an equation for it: $a_n=1+2+3+\\ldots+n$.",
        "$Final\\ Answer.$",
        "For the first step, we seek an expression for $a_n$ that allows us to determine the value of the $n^{\\text{th}}$ triangular number without having to sum the first $n$ positive integers.\nWe see that the $n^{\\text{th}}$ triangular number is equal to the sum of the first $n$ positive integers.",
        "We note that this sum is equal to $1+2+3+\\ldots+(n-1)+n$.\nThis can be expressed more compactly as $\\frac{1}{2}n(n+1)$, using the formula for the sum of an arithmetic series.",
        "We can evaluate this expression for $n=20$ by substituting $n=20$ into the formula, giving us $\\frac{1}{2}(20)(20+1)=\\frac{1}{2}(20)(21)=\\boxed{210}$.",
        "The next step is:\nWe can evaluate this expression for $n=20$ by substituting $n=20$ into the formula, giving us $\\frac{1}{2}(20)(20+1)=\\frac{1}{2}(20)(21)=\\boxed{210}$.",
        "The next step is: Final Answer."
    ],
    "full_steps": [
        [
            "The $n^{\\text{th}}$ triangular number is the sum of the first $n$ positive integers, so we can write an equation for it: $a_n=1+2+3+\\ldots+n$.",
            1
        ],
        [
            "$Final\\ Answer.$",
            1
        ],
        [
            "For the first step, we seek an expression for $a_n$ that allows us to determine the value of the $n^{\\text{th}}$ triangular number without having to sum the first $n$ positive integers.\nWe see that the $n^{\\text{th}}$ triangular number is equal to the sum of the first $n$ positive integers.",
            1
        ],
        [
            "We note that this sum is equal to $1+2+3+\\ldots+(n-1)+n$.\nThis can be expressed more compactly as $\\frac{1}{2}n(n+1)$, using the formula for the sum of an arithmetic series.",
            1
        ],
        [
            "We can evaluate this expression for $n=20$ by substituting $n=20$ into the formula, giving us $\\frac{1}{2}(20)(20+1)=\\frac{1}{2}(20)(21)=\\boxed{210}$.",
            1
        ],
        [
            "The next step is:\nWe can evaluate this expression for $n=20$ by substituting $n=20$ into the formula, giving us $\\frac{1}{2}(20)(20+1)=\\frac{1}{2}(20)(21)=\\boxed{210}$.",
            1
        ],
        [
            "The next step is: Final Answer.",
            1
        ]
    ],
    "time": 93.1541211605072,
    "total_tokens": 6429,
    "final_answer_tokens": 582,
    "model": "meta-llama/Llama-Vision-Free"
}