{
    "problem": "Evaluate $\\log_21$.",
    "level": "Level 2",
    "type": "Algebra",
    "solution": "We have $2^0=1$, so $\\log_2 1 = \\boxed{0}$.",
    "is_solved": true,
    "model_solution": "## Step 1: Recall the definition of a logarithm\n$\\log_ba=c$ means that $b^c=a$.\n\nThe final answer is: $\\boxed{0}$",
    "steps": [
        "## Step 1: Recall the definition of a logarithm\n$\\log_ba=c$ means that $b^c=a$.\n\nThe final answer is: $\\boxed{0}$"
    ],
    "full_steps": [
        [
            "## Step 1: Recall the definition of a logarithm\n$\\log_ba=c$ means that $b^c=a$.\n\nThe final answer is: $\\boxed{0}$",
            1
        ]
    ],
    "time": 14.088271856307983,
    "total_tokens": 199,
    "final_answer_tokens": 82,
    "model": "meta-llama/Llama-Vision-Free"
}