{
    "problem": "For a given constant $b > 10,$ there are two possible triangles $ABC$ satisfying $AB = 10,$ $AC = b,$ and $\\sin B = \\frac{3}{5}.$  Find the positive difference between the lengths of side $\\overline{BC}$ in these two triangles.",
    "level": "Level 5",
    "type": "Precalculus",
    "solution": "We have that\n\\[\\cos^2 B = 1 - \\sin^2 B = \\frac{16}{25},\\]so $\\cos B = \\pm \\frac{4}{5}.$\n\nFor $\\cos B = \\frac{4}{5},$ let $a_1 = BC.$  Then by the Law of Cosines,\n\\[b^2 = a_1^2 + 100 - 20a_1 \\cdot \\frac{4}{5} = a_1^2 - 16a_1 + 100.\\]For $\\cos B = -\\frac{4}{5},$ let $a_2 = BC.$  Then by the Law of Cosines,\n\\[b^2 = a_2^2 + 100 - 20a_2 \\cdot \\left( -\\frac{4}{5} \\right) = a_2^2 + 16a_2 + 100.\\]Subtracting these equations, we get\n\\[a_2^2 - a_1^2 + 16a_2 + 16a_1 = 0.\\]We can factor as $(a_2 - a_1)(a_2 + a_1) + 16(a_2 + a_1) = 0.$  Since $a_1 + a_2$ is positive, we can safely divide both sides by $a_1 + a_2,$ to get\n\\[a_2 - a_1 + 16 = 0.\\]Hence, $a_1 - a_2 = \\boxed{16}.$",
    "is_solved": true,
    "model_solution": "Step 1:  The problem involves finding the positive difference between the lengths of side $\\overline{BC}$ in two triangles, given certain conditions. We are given that $AB = 10,$ $AC = b,$ and $\\sin B = \\frac{3}{5}.$\nStep 2:  The first step is to apply the Law of Sines to triangle $ABC$. This law states that for any triangle with sides $a,$ $b,$ and $c,$ and opposite angles $A,$ $B,$ and $C$ respectively, $\\frac{a}{\\sin A} = \\frac{b}{\\sin B} = \\frac{c}{\\sin C}$.\nStep 3:  In the context of triangle $ABC$, we have $\\frac{AB}{\\sin C} = \\frac{AC}{\\sin B}$, which can be rewritten as $\\sin C = \\frac{AB \\cdot \\sin B}{AC}$.\nStep 4:  Substituting the given values, we get $\\sin C = \\frac{10 \\cdot \\frac{3}{5}}{b} = \\frac{6}{b}$.\nStep 5:\nStep 6:  Since $C$ is acute, we have $\\cos B = \\sqrt{1 - \\sin^2 B} = \\frac{4}{5}.$ If $BC$ is the longer side, then $\\cos C = \\frac{BC - 10 \\cos B}{b - 10 \\cos B}$, and if $BC$ is the shorter side, then $\\cos C = \\frac{10 \\cos B - BC}{10 \\cos B - b}$.\nWe can solve for $\\cos C$ and then use the identity $\\cos^2 C = 1 - \\sin^2 C$ to find the value of $\\cos C$.\nThen we can use the formula $\\cos C = \\frac{adjacent}{hypotenuse}$ to find the length of $BC$ in both cases.\nStep 6: $\\cos C = \\frac{4b - 40}{b^2 - 80b + 400}.$\nSince $\\cos C = \\frac{4b - 40}{b^2 - 80b + 400},$ and $\\cos C = 1 - \\sin^2 C = 1 - \\frac{36}{b^2},$ we have $1 - \\frac{36}{b^2} = \\frac{4b - 40}{b^2 - 80b + 400}$.\n\nFinal Answer.",
    "steps": [
        "Step 1:  The problem involves finding the positive difference between the lengths of side $\\overline{BC}$ in two triangles, given certain conditions. We are given that $AB = 10,$ $AC = b,$ and $\\sin B = \\frac{3}{5}.$\nStep 2:  The first step is to apply the Law of Sines to triangle $ABC$. This law states that for any triangle with sides $a,$ $b,$ and $c,$ and opposite angles $A,$ $B,$ and $C$ respectively, $\\frac{a}{\\sin A} = \\frac{b}{\\sin B} = \\frac{c}{\\sin C}$.\nStep 3:  In the context of triangle $ABC$, we have $\\frac{AB}{\\sin C} = \\frac{AC}{\\sin B}$, which can be rewritten as $\\sin C = \\frac{AB \\cdot \\sin B}{AC}$.\nStep 4:  Substituting the given values, we get $\\sin C = \\frac{10 \\cdot \\frac{3}{5}}{b} = \\frac{6}{b}$.\nStep 5:",
        "Step 6:  Since $C$ is acute, we have $\\cos B = \\sqrt{1 - \\sin^2 B} = \\frac{4}{5}.$ If $BC$ is the longer side, then $\\cos C = \\frac{BC - 10 \\cos B}{b - 10 \\cos B}$, and if $BC$ is the shorter side, then $\\cos C = \\frac{10 \\cos B - BC}{10 \\cos B - b}$.\nWe can solve for $\\cos C$ and then use the identity $\\cos^2 C = 1 - \\sin^2 C$ to find the value of $\\cos C$.\nThen we can use the formula $\\cos C = \\frac{adjacent}{hypotenuse}$ to find the length of $BC$ in both cases.",
        "Step 6: $\\cos C = \\frac{4b - 40}{b^2 - 80b + 400}.$",
        "Since $\\cos C = \\frac{4b - 40}{b^2 - 80b + 400},$ and $\\cos C = 1 - \\sin^2 C = 1 - \\frac{36}{b^2},$ we have $1 - \\frac{36}{b^2} = \\frac{4b - 40}{b^2 - 80b + 400}$.\n\nFinal Answer."
    ],
    "full_steps": [
        [
            "Step 1:  The problem involves finding the positive difference between the lengths of side $\\overline{BC}$ in two triangles, given certain conditions. We are given that $AB = 10,$ $AC = b,$ and $\\sin B = \\frac{3}{5}.$\nStep 2:  The first step is to apply the Law of Sines to triangle $ABC$. This law states that for any triangle with sides $a,$ $b,$ and $c,$ and opposite angles $A,$ $B,$ and $C$ respectively, $\\frac{a}{\\sin A} = \\frac{b}{\\sin B} = \\frac{c}{\\sin C}$.\nStep 3:  In the context of triangle $ABC$, we have $\\frac{AB}{\\sin C} = \\frac{AC}{\\sin B}$, which can be rewritten as $\\sin C = \\frac{AB \\cdot \\sin B}{AC}$.\nStep 4:  Substituting the given values, we get $\\sin C = \\frac{10 \\cdot \\frac{3}{5}}{b} = \\frac{6}{b}$.\nStep 5:",
            1
        ],
        [
            "Step 6:  Since $C$ is acute, we have $\\cos B = \\sqrt{1 - \\sin^2 B} = \\frac{4}{5}.$ If $BC$ is the longer side, then $\\cos C = \\frac{BC - 10 \\cos B}{b - 10 \\cos B}$, and if $BC$ is the shorter side, then $\\cos C = \\frac{10 \\cos B - BC}{10 \\cos B - b}$.\nWe can solve for $\\cos C$ and then use the identity $\\cos^2 C = 1 - \\sin^2 C$ to find the value of $\\cos C$.\nThen we can use the formula $\\cos C = \\frac{adjacent}{hypotenuse}$ to find the length of $BC$ in both cases.",
            1
        ],
        [
            "Step 6: $\\cos C = \\frac{4b - 40}{b^2 - 80b + 400}.$",
            1
        ],
        [
            "Since $\\cos C = \\frac{4b - 40}{b^2 - 80b + 400},$ and $\\cos C = 1 - \\sin^2 C = 1 - \\frac{36}{b^2},$ we have $1 - \\frac{36}{b^2} = \\frac{4b - 40}{b^2 - 80b + 400}$.\n\nFinal Answer.",
            1
        ]
    ],
    "time": 51.01741433143616,
    "total_tokens": 4352,
    "final_answer_tokens": 668,
    "model": "meta-llama/Llama-Vision-Free"
}