{
    "problem": "Suppose $a$ and $b$ are positive integers, neither of which is a multiple of 3.  Find the least possible remainder when $a^2 + b^2$ is divided by 3.",
    "level": "Level 2",
    "type": "Number Theory",
    "solution": "Note that $1^2 \\equiv 2^2 \\equiv 1 \\pmod{3}$.  The only possible modulo 3 residue for a square that isn't a multiple of 3 is 1.  Therefore, $a^2 + b^2 \\equiv 1 + 1 \\equiv \\boxed{2} \\pmod{3}$.",
    "is_solved": false,
    "model_solution": "Step 1: Since a and b are positive integers that are not multiples of 3, we can represent them as a = 3m + 1 and b = 3n + 1, where m and n are non-negative integers.\nStep 2: We can now compute $a^2 + b^2$ by substituting the expressions for a and b:\n$a^2 + b^2 = (3m + 1)^2 + (3n + 1)^2$\n$= 9m^2 + 6m + 1 + 9n^2 + 6n + 1$\n$= 9(m^2 + n^2 + m + n) + 2$\nStep 3: When $a^2 + b^2$ is divided by 3, the remainder is the remainder of $2 \\div 3$.\nStep 4: The remainder of $2 \\div 3$ is 2.\nStep 5: Since the remainder of 2 divided by 3 is 2, the least possible remainder when $a^2 + b^2$ is divided by 3 is 2.\nStep 6: The remainder when $a^2 + b^2$ is divided by 3 is indeed 2.\nStep 7: We can check this result by testing specific values for a and b, such as a = 1 and b = 2.\nStep 8: We can calculate $(1)^2 + (2)^2 = 1 + 4 = 5$, and $5 \\div 3$ has a remainder of 2.\nStep 9: We have verified that the remainder when $a^2 + b^2$ is divided by 3 is indeed 2.\nStep 2: We can now compute $a^2 + b^2$ by substituting the expressions for a and b: $a^2 + b^2 = (3m + 1)^2 + (3n + 1)^2$",
    "steps": [
        "Step 1: Since a and b are positive integers that are not multiples of 3, we can represent them as a = 3m + 1 and b = 3n + 1, where m and n are non-negative integers.",
        "Step 2: We can now compute $a^2 + b^2$ by substituting the expressions for a and b:\n$a^2 + b^2 = (3m + 1)^2 + (3n + 1)^2$\n$= 9m^2 + 6m + 1 + 9n^2 + 6n + 1$\n$= 9(m^2 + n^2 + m + n) + 2$",
        "Step 3: When $a^2 + b^2$ is divided by 3, the remainder is the remainder of $2 \\div 3$.",
        "Step 4: The remainder of $2 \\div 3$ is 2.",
        "Step 5: Since the remainder of 2 divided by 3 is 2, the least possible remainder when $a^2 + b^2$ is divided by 3 is 2.",
        "Step 6: The remainder when $a^2 + b^2$ is divided by 3 is indeed 2.",
        "Step 7: We can check this result by testing specific values for a and b, such as a = 1 and b = 2.",
        "Step 8: We can calculate $(1)^2 + (2)^2 = 1 + 4 = 5$, and $5 \\div 3$ has a remainder of 2.",
        "Step 9: We have verified that the remainder when $a^2 + b^2$ is divided by 3 is indeed 2.",
        "Step 2: We can now compute $a^2 + b^2$ by substituting the expressions for a and b: $a^2 + b^2 = (3m + 1)^2 + (3n + 1)^2$"
    ],
    "full_steps": [
        [
            "Step 1: Since a and b are positive integers that are not multiples of 3, we can represent them as a = 3m + 1 and b = 3n + 1, where m and n are non-negative integers.",
            1
        ],
        [
            "Step 2: We can now compute $a^2 + b^2$ by substituting the expressions for a and b:\n$a^2 + b^2 = (3m + 1)^2 + (3n + 1)^2$\n$= 9m^2 + 6m + 1 + 9n^2 + 6n + 1$\n$= 9(m^2 + n^2 + m + n) + 2$",
            1
        ],
        [
            "Step 3: When $a^2 + b^2$ is divided by 3, the remainder is the remainder of $2 \\div 3$.",
            1
        ],
        [
            "Step 4: The remainder of $2 \\div 3$ is 2.",
            1
        ],
        [
            "Step 5: Since the remainder of 2 divided by 3 is 2, the least possible remainder when $a^2 + b^2$ is divided by 3 is 2.",
            1
        ],
        [
            "Step 6: The remainder when $a^2 + b^2$ is divided by 3 is indeed 2.",
            1
        ],
        [
            "Step 7: We can check this result by testing specific values for a and b, such as a = 1 and b = 2.",
            1
        ],
        [
            "Step 8: We can calculate $(1)^2 + (2)^2 = 1 + 4 = 5$, and $5 \\div 3$ has a remainder of 2.",
            1
        ],
        [
            "Step 9: We have verified that the remainder when $a^2 + b^2$ is divided by 3 is indeed 2.",
            1
        ],
        [
            "Step 2: We can now compute $a^2 + b^2$ by substituting the expressions for a and b: $a^2 + b^2 = (3m + 1)^2 + (3n + 1)^2$",
            1
        ]
    ],
    "time": 137.5589792728424,
    "total_tokens": 7275,
    "final_answer_tokens": 0,
    "model": "meta-llama/Llama-Vision-Free"
}