{
    "problem": "Find the constant coefficient when the polynomial $3(x - 4) + 2(x^2 - x + 7) - 5(x - 1)$ is simplified.",
    "level": "Level 4",
    "type": "Algebra",
    "solution": "The constant coefficient in $3(x - 4) + 2(x^2 - x + 7) - 5(x - 1)$ is $3 \\cdot (-4) + 2 \\cdot 7 - 5 \\cdot (-1) = \\boxed{7}$.",
    "is_solved": true,
    "model_solution": "## Step 1: Distribute the numbers outside the parentheses to the terms inside.\n$3(x - 4) + 2(x^2 - x + 7) - 5(x - 1) = 3x - 12 + 2x^2 - 2x + 14 - 5x + 5$\n## Step 2: Combine like terms.\n$3x - 12 + 2x^2 - 2x - 5x + 14 + 5 = 2x^2 + (3x - 2x - 5x) + (14 - 12 + 5)$\n## Step 3: Simplify the expression.\n$2x^2 + (3x - 2x - 5x) + (14 - 12 + 5) = 2x^2 -4x + 7$\n## Step 4: Identify the constant term in the expression $2x^2 - 4x + 7$.\n$7$\n$7$\n## Step 5: Determine the constant coefficient.\n$7$\n## Step 6: The constant coefficient is the number that multiplies the constant term in the expression, which is 7.\n$7$\n## Step 7: The constant coefficient is 7.\n## Step 8: Final Answer: $\\boxed{7}$",
    "steps": [
        "## Step 1: Distribute the numbers outside the parentheses to the terms inside.\n$3(x - 4) + 2(x^2 - x + 7) - 5(x - 1) = 3x - 12 + 2x^2 - 2x + 14 - 5x + 5$",
        "## Step 2: Combine like terms.\n$3x - 12 + 2x^2 - 2x - 5x + 14 + 5 = 2x^2 + (3x - 2x - 5x) + (14 - 12 + 5)$",
        "## Step 3: Simplify the expression.\n$2x^2 + (3x - 2x - 5x) + (14 - 12 + 5) = 2x^2 -4x + 7$",
        "## Step 4: Identify the constant term in the expression $2x^2 - 4x + 7$.\n$7$",
        "$7$",
        "## Step 5: Determine the constant coefficient.\n$7$",
        "## Step 6: The constant coefficient is the number that multiplies the constant term in the expression, which is 7.\n$7$",
        "## Step 7: The constant coefficient is 7.",
        "## Step 8: Final Answer: $\\boxed{7}$"
    ],
    "full_steps": [
        [
            "## Step 1: Distribute the numbers outside the parentheses to the terms inside.\n$3(x - 4) + 2(x^2 - x + 7) - 5(x - 1) = 3x - 12 + 2x^2 - 2x + 14 - 5x + 5$",
            1
        ],
        [
            "## Step 2: Combine like terms.\n$3x - 12 + 2x^2 - 2x - 5x + 14 + 5 = 2x^2 + (3x - 2x - 5x) + (14 - 12 + 5)$",
            1
        ],
        [
            "## Step 3: Simplify the expression.\n$2x^2 + (3x - 2x - 5x) + (14 - 12 + 5) = 2x^2 -4x + 7$",
            1
        ],
        [
            "## Step 4: Identify the constant term in the expression $2x^2 - 4x + 7$.\n$7$",
            1
        ],
        [
            "$7$",
            1
        ],
        [
            "## Step 5: Determine the constant coefficient.\n$7$",
            1
        ],
        [
            "## Step 6: The constant coefficient is the number that multiplies the constant term in the expression, which is 7.\n$7$",
            1
        ],
        [
            "## Step 7: The constant coefficient is 7.",
            1
        ],
        [
            "## Step 8: Final Answer: $\\boxed{7}$",
            1
        ]
    ],
    "time": 123.53462052345276,
    "total_tokens": 5595,
    "final_answer_tokens": 382,
    "model": "meta-llama/Llama-Vision-Free"
}